larray_eurostat/__init__.py
larray_eurostat/tsv.py
larray_eurostat/tests/__init__.py
larray_eurostat/tests/test_tsv.py
larray_eurostat-0.35.dist-info/licenses/LICENSE
larray_eurostat-0.35.dist-info/METADATA
larray_eurostat-0.35.dist-info/WHEEL
larray_eurostat-0.35.dist-info/top_level.txt
larray_eurostat-0.35.dist-info/RECORD
