Metadata-Version: 2.4
Name: larray_eurostat
Version: 0.35
Summary: Additional package to import Eurostat files using LArray
Author: Geert Bryon, Yannick Van den Abbeel
Author-email: Gaetan de Menten <gdementen@gmail.com>, Alix Damman <ald@plan.be>
License-Expression: GPL-3.0-only
Project-URL: Homepage, https://github.com/larray-project/larray_eurostat
Project-URL: Repository, https://github.com/larray-project/larray_eurostat
Project-URL: Issues, https://github.com/larray-project/larray_eurostat/issues
Classifier: Development Status :: 4 - Beta
Classifier: Operating System :: OS Independent
Classifier: Intended Audience :: Science/Research
Classifier: Intended Audience :: Developers
Classifier: Programming Language :: Python
Classifier: Programming Language :: Python :: 3
Classifier: Programming Language :: Python :: 3.9
Classifier: Programming Language :: Python :: 3.10
Classifier: Programming Language :: Python :: 3.11
Classifier: Programming Language :: Python :: 3.12
Classifier: Programming Language :: Python :: 3.13
Classifier: Programming Language :: Python :: 3.14
Classifier: Topic :: Scientific/Engineering
Classifier: Topic :: Software Development :: Libraries
Requires-Python: >=3.9
License-File: LICENSE
Requires-Dist: larray
Provides-Extra: test
Requires-Dist: pytest; extra == "test"
Dynamic: license-file
